README.md
setup.py
src/testit.py
src/testit_python_commons/__init__.py
src/testit_python_commons/app_properties.py
src/testit_python_commons/decorators.py
src/testit_python_commons/dynamic_methods.py
src/testit_python_commons/step.py
src/testit_python_commons.egg-info/PKG-INFO
src/testit_python_commons.egg-info/SOURCES.txt
src/testit_python_commons.egg-info/dependency_links.txt
src/testit_python_commons.egg-info/requires.txt
src/testit_python_commons.egg-info/top_level.txt
src/testit_python_commons/client/__init__.py
src/testit_python_commons/client/api_client.py
src/testit_python_commons/client/client_configuration.py
src/testit_python_commons/client/converter.py
src/testit_python_commons/client/helpers/__init__.py
src/testit_python_commons/client/helpers/bulk_autotest_helper.py
src/testit_python_commons/client/helpers/threads_manager.py
src/testit_python_commons/client/models/__init__.py
src/testit_python_commons/client/models/threads_for_create_and_result.py
src/testit_python_commons/client/models/threads_for_update_and_result.py
src/testit_python_commons/models/__init__.py
src/testit_python_commons/models/adapter_mode.py
src/testit_python_commons/models/fixture.py
src/testit_python_commons/models/link.py
src/testit_python_commons/models/link_type.py
src/testit_python_commons/models/outcome_type.py
src/testit_python_commons/models/step_result.py
src/testit_python_commons/models/test_result.py
src/testit_python_commons/models/test_result_with_all_fixture_step_results_model.py
src/testit_python_commons/services/__init__.py
src/testit_python_commons/services/adapter_manager.py
src/testit_python_commons/services/adapter_manager_configuration.py
src/testit_python_commons/services/fixture_manager.py
src/testit_python_commons/services/fixture_storage.py
src/testit_python_commons/services/logger.py
src/testit_python_commons/services/plugin_manager.py
src/testit_python_commons/services/retry.py
src/testit_python_commons/services/step_manager.py
src/testit_python_commons/services/step_result_storage.py
src/testit_python_commons/services/utils.py
src/testit_python_commons/utils/__init__.py
src/testit_python_commons/utils/html_escape_utils.py
tests/test_app_properties.py
tests/test_dynamic_methods.py
