Metadata-Version: 2.4
Name: testit-python-commons
Version: 3.11.0.post560
Summary: Python commons for Test IT
Home-page: https://github.com/testit-tms/adapters-python/
Author: Integration team
Author-email: integrations@testit.software
License: Apache-2.0
Classifier: Programming Language :: Python :: 3
Classifier: Programming Language :: Python :: 3.6
Classifier: Programming Language :: Python :: 3.7
Classifier: Programming Language :: Python :: 3.8
Classifier: Programming Language :: Python :: 3.9
Classifier: Programming Language :: Python :: 3.10
Classifier: Programming Language :: Python :: 3.11
Classifier: Programming Language :: Python :: 3.12
Requires-Dist: pluggy
Requires-Dist: tomli
Requires-Dist: testit-api-client==7.4.0.post560
Dynamic: author
Dynamic: author-email
Dynamic: classifier
Dynamic: description
Dynamic: description-content-type
Dynamic: home-page
Dynamic: license
Dynamic: requires-dist
Dynamic: summary
